[
    {
        "text": "Research Questions and Hypotheses",
        "score": 0.984908938407898,
        "box": [
            52,
            41,
            789,
            88
        ]
    },
    {
        "text": "Research Question 1:What is the relation between Emotional Stability(C), Rule-Consciousness",
        "score": 0.9709627628326416,
        "box": [
            78,
            134,
            871,
            155
        ]
    },
    {
        "text": "(G), and Tough-Mindedness (TM) and athletic performance outcomes?",
        "score": 0.9549255967140198,
        "box": [
            81,
            155,
            647,
            172
        ]
    },
    {
        "text": "Hypothesis 1:Athletes with high levels of Emotional Stability (C),Rule-Consciousness(G), and",
        "score": 0.9502529501914978,
        "box": [
            80,
            179,
            860,
            196
        ]
    },
    {
        "text": "Tough-Mindedness (TM) will have higher athletic performance scores on all coach ratings,excluding",
        "score": 0.9664608836174011,
        "box": [
            78,
            196,
            885,
            216
        ]
    },
    {
        "text": "athletic ability,andpercentage of games started ina season",
        "score": 0.946918249130249,
        "box": [
            81,
            216,
            568,
            233
        ]
    },
    {
        "text": "Research Question 2:Can Emotional Stability (C),Rule-Consciousness(G),and Tough-Mindedness",
        "score": 0.9543659687042236,
        "box": [
            80,
            262,
            897,
            279
        ]
    },
    {
        "text": "(TM)predict athletic performance outcomes?",
        "score": 0.9774249792098999,
        "box": [
            81,
            282,
            445,
            299
        ]
    },
    {
        "text": "Hypothesis 2:Emotional stability (C), Rule-Consciousness(G), and Tough-Mindedness (TM) will",
        "score": 0.9481942057609558,
        "box": [
            81,
            306,
            865,
            323
        ]
    },
    {
        "text": "significantly predict the composite coach rating of athletic performance and percent of games",
        "score": 0.9589757323265076,
        "box": [
            81,
            325,
            836,
            341
        ]
    },
    {
        "text": "started, when athletic ability is statistically controlled",
        "score": 0.9674243330955505,
        "box": [
            81,
            343,
            510,
            360
        ]
    },
    {
        "text": "|California",
        "score": 0.9607488512992859,
        "box": [
            44,
            469,
            128,
            486
        ]
    },
    {
        "text": "Lutheran",
        "score": 0.9967199563980103,
        "box": [
            43,
            481,
            123,
            505
        ]
    },
    {
        "text": "University",
        "score": 0.9823607206344604,
        "box": [
            42,
            499,
            127,
            522
        ]
    }
]